Metadata-Version: 2.1
Name: aspcmds
Version: 1.5
License-File: LICENCE.txt
